<?xml version="1.0" encoding="UTF-8"?>
<openerp>
    <data>
        <record id="view_account_invoice_discount_form" model="ir.ui.view">
            <field name="name">account.invoice.discount.form.view</field>
            <field name="model">account.invoice</field>
            <field name="inherit_id" ref="account.invoice_supplier_form"/>
            <field name="arch" type="xml">
                <xpath expr="//group[@class='oe_subtotal_footer oe_right']" position="after">
                    <group>
                        <label for="discount_method"/>
                        <div>
                            <field name="discount_method" class="oe_inline"/>
                        </div>
                         <label for="discount_amount"/>
                        <div>
                            <field name="discount_amount" class="oe_inline"/>
                            <label string="%%"
                                attrs="{'invisible': [('discount_method', '!=', 'per')]}" class="oe_inline"/>
                         </div>
                    </group>
                </xpath>
                <field name="amount_untaxed" position="after">
                     <field name="discount_amt" widget="monetary" options="{'currency_field': 'currency_id'}"/>
                </field>
            </field>
        </record>
    </data>
</openerp>
